LaFamilia/__init__.py
LaFamilia/teste.py
LaFamilia013-0.0.1.dist-info/LICENCE
LaFamilia013-0.0.1.dist-info/METADATA
LaFamilia013-0.0.1.dist-info/WHEEL
LaFamilia013-0.0.1.dist-info/top_level.txt
LaFamilia013-0.0.1.dist-info/RECORD
