Metadata-Version: 2.1
Name: LaFamilia013
Version: 0.0.1
Summary: Apenas teste
Author: Matheus Nascimento
Author-email: matheus.mn87@gmail.com
License: MIT License
Keywords: LaFamilia013
License-File: LICENCE
Requires-Dist: requests
